[
    {
        "id": 580,
        "avatar": "/storage/avatars/d2ddffcb2eced6a4d5486dc99d440d1a.png",
        "name": "Surveillance",
        "static_points": 30,
        "sp_flag": 0,
        "os": "Linux",
        "points": 30,
        "star": 4.3,
        "release": "2023-12-09T17:00:00.000000Z",
        "easy_month": 0,
        "poweroff": 0,
        "free": true,
        "difficulty": 45,
        "difficultyText": "Medium",
        "user_owns_count": 1080,
        "authUserInUserOwns": false,
        "root_owns_count": 815,
        "authUserHasReviewed": false,
        "authUserInRootOwns": false,
        "isTodo": false,
        "is_competitive": true,
        "active": null,
        "feedbackForChart": {
            "counterCake": 55,
            "counterVeryEasy": 66,
            "counterEasy": 240,
            "counterTooEasy": 264,
            "counterMedium": 327,
            "counterBitHard": 174,
            "counterHard": 102,
            "counterTooHard": 26,
            "counterExHard": 6,
            "counterBrainFuck": 19
        },
        "ip": null,
        "playInfo": {
            "isActive": null,
            "expires_at": null
        },
        "labels": [
            {
                "color": "blue",
                "name": "SEASONAL"
            }
        ],
        "recommended": 0
    },
    {
        "id": 579,
        "avatar": "/storage/avatars/50788eb40c2464d6554a3cb15bd2e301.png",
        "name": "Ouija",
        "static_points": 50,
        "sp_flag": 0,
        "os": "Linux",
        "points": 50,
        "star": 2.3,
        "release": "2023-12-02T17:00:00.000000Z",
        "easy_month": 0,
        "poweroff": 0,
        "free": true,
        "difficulty": 84,
        "difficultyText": "Insane",
        "user_owns_count": 757,
        "authUserInUserOwns": false,
        "root_owns_count": 594,
        "authUserHasReviewed": false,
        "authUserInRootOwns": false,
        "isTodo": false,
        "is_competitive": false,
        "active": null,
        "feedbackForChart": {
            "counterCake": 21,
            "counterVeryEasy": 3,
            "counterEasy": 5,
            "counterTooEasy": 11,
            "counterMedium": 24,
            "counterBitHard": 43,
            "counterHard": 123,
            "counterTooHard": 196,
            "counterExHard": 159,
            "counterBrainFuck": 360
        },
        "ip": null,
        "playInfo": {
            "isActive": null,
            "expires_at": null
        },
        "labels": [],
        "recommended": 0
    },
    {
        "id": 577,
        "avatar": "/storage/avatars/2565d292772abc4a2d774117cf4d36ff.png",
        "name": "Devvortex",
        "static_points": 20,
        "sp_flag": 0,
        "os": "Linux",
        "points": 20,
        "star": 4.7,
        "release": "2023-11-25T17:00:00.000000Z",
        "easy_month": 0,
        "poweroff": 0,
        "free": true,
        "difficulty": 32,
        "difficultyText": "Easy",
        "user_owns_count": 5048,
        "authUserInUserOwns": false,
        "root_owns_count": 4821,
        "authUserHasReviewed": false,
        "authUserInRootOwns": false,
        "isTodo": false,
        "is_competitive": false,
        "active": null,
        "feedbackForChart": {
            "counterCake": 735,
            "counterVeryEasy": 1184,
            "counterEasy": 2592,
            "counterTooEasy": 1179,
            "counterMedium": 500,
            "counterBitHard": 207,
            "counterHard": 114,
            "counterTooHard": 37,
            "counterExHard": 12,
            "counterBrainFuck": 50
        },
        "ip": null,
        "playInfo": {
            "isActive": null,
            "expires_at": null
        },
        "labels": [],
        "recommended": 0
    },
    {
        "id": 576,
        "avatar": "/storage/avatars/e980d18b909fa0ba8f519cf9777fd413.png",
        "name": "Hospital",
        "static_points": 30,
        "sp_flag": 0,
        "os": "Windows",
        "points": 30,
        "star": 4.7,
        "release": "2023-11-18T17:00:00.000000Z",
        "easy_month": 0,
        "poweroff": 0,
        "free": true,
        "difficulty": 48,
        "difficultyText": "Medium",
        "user_owns_count": 2057,
        "authUserInUserOwns": false,
        "root_owns_count": 1985,
        "authUserHasReviewed": false,
        "authUserInRootOwns": false,
        "isTodo": false,
        "is_competitive": false,
        "active": null,
        "feedbackForChart": {
            "counterCake": 138,
            "counterVeryEasy": 135,
            "counterEasy": 359,
            "counterTooEasy": 457,
            "counterMedium": 795,
            "counterBitHard": 493,
            "counterHard": 286,
            "counterTooHard": 78,
            "counterExHard": 28,
            "counterBrainFuck": 46
        },
        "ip": null,
        "playInfo": {
            "isActive": null,
            "expires_at": null
        },
        "labels": [],
        "recommended": 0
    },
    {
        "id": 575,
        "avatar": "/storage/avatars/e936dbb185607fb8957679b26b0a0930.png",
        "name": "Napper",
        "static_points": 40,
        "sp_flag": 0,
        "os": "Windows",
        "points": 40,
        "star": 4.4,
        "release": "2023-11-11T17:00:00.000000Z",
        "easy_month": 0,
        "poweroff": 0,
        "free": true,
        "difficulty": 68,
        "difficultyText": "Hard",
        "user_owns_count": 961,
        "authUserInUserOwns": false,
        "root_owns_count": 711,
        "authUserHasReviewed": false,
        "authUserInRootOwns": false,
        "isTodo": false,
        "is_competitive": false,
        "active": null,
        "feedbackForChart": {
            "counterCake": 26,
            "counterVeryEasy": 9,
            "counterEasy": 30,
            "counterTooEasy": 77,
            "counterMedium": 113,
            "counterBitHard": 168,
            "counterHard": 321,
            "counterTooHard": 196,
            "counterExHard": 90,
            "counterBrainFuck": 119
        },
        "ip": null,
        "playInfo": {
            "isActive": null,
            "expires_at": null
        },
        "labels": [],
        "recommended": 0
    },
    {
        "id": 574,
        "avatar": "/storage/avatars/57b977ea744af01a5454c8643a850e59.png",
        "name": "Codify",
        "static_points": 20,
        "sp_flag": 0,
        "os": "Linux",
        "points": 20,
        "star": 4.4,
        "release": "2023-11-04T17:00:00.000000Z",
        "easy_month": 0,
        "poweroff": 0,
        "free": true,
        "difficulty": 34,
        "difficultyText": "Easy",
        "user_owns_count": 7659,
        "authUserInUserOwns": false,
        "root_owns_count": 7134,
        "authUserHasReviewed": false,
        "authUserInRootOwns": false,
        "isTodo": false,
        "is_competitive": false,
        "active": null,
        "feedbackForChart": {
            "counterCake": 973,
            "counterVeryEasy": 1308,
            "counterEasy": 3324,
            "counterTooEasy": 2195,
            "counterMedium": 876,
            "counterBitHard": 302,
            "counterHard": 215,
            "counterTooHard": 70,
            "counterExHard": 19,
            "counterBrainFuck": 67
        },
        "ip": null,
        "playInfo": {
            "isActive": null,
            "expires_at": null
        },
        "labels": [],
        "recommended": 0
    },
    {
        "id": 573,
        "avatar": "/storage/avatars/3637f8cd2b3850f40cb6d16b7c39d43b.png",
        "name": "Appsanity",
        "static_points": 40,
        "sp_flag": 0,
        "os": "Windows",
        "points": 40,
        "star": 4.5,
        "release": "2023-10-28T16:00:00.000000Z",
        "easy_month": 0,
        "poweroff": 0,
        "free": true,
        "difficulty": 66,
        "difficultyText": "Hard",
        "user_owns_count": 1085,
        "authUserInUserOwns": false,
        "root_owns_count": 948,
        "authUserHasReviewed": false,
        "authUserInRootOwns": false,
        "isTodo": false,
        "is_competitive": false,
        "active": null,
        "feedbackForChart": {
            "counterCake": 29,
            "counterVeryEasy": 18,
            "counterEasy": 32,
            "counterTooEasy": 83,
            "counterMedium": 161,
            "counterBitHard": 236,
            "counterHard": 425,
            "counterTooHard": 245,
            "counterExHard": 95,
            "counterBrainFuck": 78
        },
        "ip": null,
        "playInfo": {
            "isActive": null,
            "expires_at": null
        },
        "labels": [],
        "recommended": 0
    },
    {
        "id": 572,
        "avatar": "/storage/avatars/5ca8f0c721a9eca6f1aeb9ff4b4bac60.png",
        "name": "Manager",
        "static_points": 30,
        "sp_flag": 0,
        "os": "Windows",
        "points": 30,
        "star": 4.6,
        "release": "2023-10-21T16:00:00.000000Z",
        "easy_month": 0,
        "poweroff": 0,
        "free": true,
        "difficulty": 49,
        "difficultyText": "Medium",
        "user_owns_count": 2837,
        "authUserInUserOwns": false,
        "root_owns_count": 2299,
        "authUserHasReviewed": false,
        "authUserInRootOwns": false,
        "isTodo": false,
        "is_competitive": false,
        "active": null,
        "feedbackForChart": {
            "counterCake": 92,
            "counterVeryEasy": 72,
            "counterEasy": 388,
            "counterTooEasy": 723,
            "counterMedium": 1001,
            "counterBitHard": 522,
            "counterHard": 323,
            "counterTooHard": 86,
            "counterExHard": 20,
            "counterBrainFuck": 41
        },
        "ip": null,
        "playInfo": {
            "isActive": null,
            "expires_at": null
        },
        "labels": [],
        "recommended": 0
    },
    {
        "id": 570,
        "avatar": "/storage/avatars/69894bcbc09fb85054b71bdc805f86bc.png",
        "name": "Drive",
        "static_points": 40,
        "sp_flag": 0,
        "os": "Linux",
        "points": 40,
        "star": 4.6,
        "release": "2023-10-14T16:00:00.000000Z",
        "easy_month": 0,
        "poweroff": 0,
        "free": true,
        "difficulty": 59,
        "difficultyText": "Hard",
        "user_owns_count": 1947,
        "authUserInUserOwns": false,
        "root_owns_count": 1718,
        "authUserHasReviewed": false,
        "authUserInRootOwns": false,
        "isTodo": false,
        "is_competitive": false,
        "active": null,
        "feedbackForChart": {
            "counterCake": 48,
            "counterVeryEasy": 39,
            "counterEasy": 146,
            "counterTooEasy": 251,
            "counterMedium": 443,
            "counterBitHard": 487,
            "counterHard": 580,
            "counterTooHard": 215,
            "counterExHard": 66,
            "counterBrainFuck": 80
        },
        "ip": null,
        "playInfo": {
            "isActive": null,
            "expires_at": null
        },
        "labels": [],
        "recommended": 0
    },
    {
        "id": 569,
        "avatar": "/storage/avatars/f86fcf4c1cfcc690b43f43e100f89718.png",
        "name": "Analytics",
        "static_points": 20,
        "sp_flag": 0,
        "os": "Linux",
        "points": 20,
        "star": 3.9,
        "release": "2023-10-07T16:00:00.000000Z",
        "easy_month": 0,
        "poweroff": 0,
        "free": true,
        "difficulty": 33,
        "difficultyText": "Easy",
        "user_owns_count": 8637,
        "authUserInUserOwns": false,
        "root_owns_count": 8161,
        "authUserHasReviewed": false,
        "authUserInRootOwns": false,
        "isTodo": false,
        "is_competitive": false,
        "active": null,
        "feedbackForChart": {
            "counterCake": 898,
            "counterVeryEasy": 1440,
            "counterEasy": 4101,
            "counterTooEasy": 2128,
            "counterMedium": 779,
            "counterBitHard": 291,
            "counterHard": 159,
            "counterTooHard": 47,
            "counterExHard": 20,
            "counterBrainFuck": 70
        },
        "ip": null,
        "playInfo": {
            "isActive": null,
            "expires_at": null
        },
        "labels": [],
        "recommended": 0
    },
    {
        "id": 568,
        "avatar": "/storage/avatars/a75ac8ed04e6e728547538bfa41cfc68.png",
        "name": "Visual",
        "static_points": 30,
        "sp_flag": 0,
        "os": "Windows",
        "points": 30,
        "star": 4.6,
        "release": "2023-09-30T16:00:00.000000Z",
        "easy_month": 0,
        "poweroff": 0,
        "free": true,
        "difficulty": 50,
        "difficultyText": "Medium",
        "user_owns_count": 1825,
        "authUserInUserOwns": false,
        "root_owns_count": 1574,
        "authUserHasReviewed": false,
        "authUserInRootOwns": false,
        "isTodo": false,
        "is_competitive": false,
        "active": null,
        "feedbackForChart": {
            "counterCake": 60,
            "counterVeryEasy": 56,
            "counterEasy": 256,
            "counterTooEasy": 537,
            "counterMedium": 656,
            "counterBitHard": 433,
            "counterHard": 244,
            "counterTooHard": 69,
            "counterExHard": 19,
            "counterBrainFuck": 57
        },
        "ip": null,
        "playInfo": {
            "isActive": null,
            "expires_at": null
        },
        "labels": [],
        "recommended": 0
    },
    {
        "id": 564,
        "avatar": "/storage/avatars/5a89d213ede5af4b4f94035fd059f976.png",
        "name": "Clicker",
        "static_points": 30,
        "sp_flag": 0,
        "os": "Linux",
        "points": 30,
        "star": 4.6,
        "release": "2023-09-23T16:00:00.000000Z",
        "easy_month": 0,
        "poweroff": 0,
        "free": true,
        "difficulty": 48,
        "difficultyText": "Medium",
        "user_owns_count": 2421,
        "authUserInUserOwns": false,
        "root_owns_count": 2352,
        "authUserHasReviewed": false,
        "authUserInRootOwns": false,
        "isTodo": false,
        "is_competitive": false,
        "active": null,
        "feedbackForChart": {
            "counterCake": 91,
            "counterVeryEasy": 72,
            "counterEasy": 376,
            "counterTooEasy": 686,
            "counterMedium": 909,
            "counterBitHard": 525,
            "counterHard": 280,
            "counterTooHard": 34,
            "counterExHard": 8,
            "counterBrainFuck": 30
        },
        "ip": null,
        "playInfo": {
            "isActive": null,
            "expires_at": null
        },
        "labels": [],
        "recommended": 0
    },
    {
        "id": 560,
        "avatar": "/storage/avatars/2ad5dcb2fb97e40f5e88a0d6fc569bdd.png",
        "name": "Rebound",
        "static_points": 50,
        "sp_flag": 0,
        "os": "Windows",
        "points": 50,
        "star": 5,
        "release": "2023-09-09T16:00:00.000000Z",
        "easy_month": 0,
        "poweroff": 0,
        "free": true,
        "difficulty": 82,
        "difficultyText": "Insane",
        "user_owns_count": 721,
        "authUserInUserOwns": false,
        "root_owns_count": 646,
        "authUserHasReviewed": false,
        "authUserInRootOwns": false,
        "isTodo": false,
        "is_competitive": false,
        "active": null,
        "feedbackForChart": {
            "counterCake": 18,
            "counterVeryEasy": 2,
            "counterEasy": 3,
            "counterTooEasy": 17,
            "counterMedium": 29,
            "counterBitHard": 51,
            "counterHard": 150,
            "counterTooHard": 175,
            "counterExHard": 181,
            "counterBrainFuck": 284
        },
        "ip": null,
        "playInfo": {
            "isActive": null,
            "expires_at": null
        },
        "labels": [],
        "recommended": 0
    },
    {
        "id": 559,
        "avatar": "/storage/avatars/eaed7cd01e84ef5c6ec7d949d1d61110.png",
        "name": "CozyHosting",
        "static_points": 20,
        "sp_flag": 0,
        "os": "Linux",
        "points": 20,
        "star": 4.5,
        "release": "2023-09-02T16:00:00.000000Z",
        "easy_month": 0,
        "poweroff": 0,
        "free": true,
        "difficulty": 32,
        "difficultyText": "Easy",
        "user_owns_count": 10621,
        "authUserInUserOwns": false,
        "root_owns_count": 10535,
        "authUserHasReviewed": false,
        "authUserInRootOwns": false,
        "isTodo": false,
        "is_competitive": false,
        "active": null,
        "feedbackForChart": {
            "counterCake": 3074,
            "counterVeryEasy": 1392,
            "counterEasy": 2968,
            "counterTooEasy": 2749,
            "counterMedium": 1211,
            "counterBitHard": 577,
            "counterHard": 382,
            "counterTooHard": 93,
            "counterExHard": 21,
            "counterBrainFuck": 85
        },
        "ip": null,
        "playInfo": {
            "isActive": null,
            "expires_at": null
        },
        "labels": [],
        "recommended": 0
    },
    {
        "id": 558,
        "avatar": "/storage/avatars/03e875ef2a39c9a2bd7538b3cfcd9b8a.png",
        "name": "Zipping",
        "static_points": 30,
        "sp_flag": 0,
        "os": "Linux",
        "points": 30,
        "star": 4.2,
        "release": "2023-08-26T16:00:00.000000Z",
        "easy_month": 0,
        "poweroff": 0,
        "free": true,
        "difficulty": 46,
        "difficultyText": "Medium",
        "user_owns_count": 3255,
        "authUserInUserOwns": false,
        "root_owns_count": 2680,
        "authUserHasReviewed": false,
        "authUserInRootOwns": false,
        "isTodo": false,
        "is_competitive": false,
        "active": null,
        "feedbackForChart": {
            "counterCake": 149,
            "counterVeryEasy": 182,
            "counterEasy": 715,
            "counterTooEasy": 925,
            "counterMedium": 942,
            "counterBitHard": 580,
            "counterHard": 343,
            "counterTooHard": 86,
            "counterExHard": 20,
            "counterBrainFuck": 65
        },
        "ip": null,
        "playInfo": {
            "isActive": null,
            "expires_at": null
        },
        "labels": [],
        "recommended": 0
    },
    {
        "id": 556,
        "avatar": "/storage/avatars/b56a5742b99e2568fa167765b1323370.png",
        "name": "Keeper",
        "static_points": 20,
        "sp_flag": 0,
        "os": "Linux",
        "points": 20,
        "star": 3.9,
        "release": "2023-08-12T16:00:00.000000Z",
        "easy_month": 0,
        "poweroff": 0,
        "free": true,
        "difficulty": 29,
        "difficultyText": "Easy",
        "user_owns_count": 18237,
        "authUserInUserOwns": false,
        "root_owns_count": 13395,
        "authUserHasReviewed": false,
        "authUserInRootOwns": false,
        "isTodo": false,
        "is_competitive": false,
        "active": null,
        "feedbackForChart": {
            "counterCake": 4007,
            "counterVeryEasy": 3770,
            "counterEasy": 6322,
            "counterTooEasy": 2985,
            "counterMedium": 1162,
            "counterBitHard": 470,
            "counterHard": 279,
            "counterTooHard": 72,
            "counterExHard": 29,
            "counterBrainFuck": 118
        },
        "ip": null,
        "playInfo": {
            "isActive": null,
            "expires_at": null
        },
        "labels": [],
        "recommended": 0
    },
    {
        "id": 552,
        "avatar": "/storage/avatars/a7f6d497c768ff770389b00e31150652.png",
        "name": "RegistryTwo",
        "static_points": 50,
        "sp_flag": 0,
        "os": "Linux",
        "points": 50,
        "star": 4.7,
        "release": "2023-07-22T16:00:00.000000Z",
        "easy_month": 0,
        "poweroff": 0,
        "free": true,
        "difficulty": 82,
        "difficultyText": "Insane",
        "user_owns_count": 563,
        "authUserInUserOwns": false,
        "root_owns_count": 536,
        "authUserHasReviewed": false,
        "authUserInRootOwns": false,
        "isTodo": false,
        "is_competitive": false,
        "active": null,
        "feedbackForChart": {
            "counterCake": 39,
            "counterVeryEasy": 2,
            "counterEasy": 4,
            "counterTooEasy": 6,
            "counterMedium": 21,
            "counterBitHard": 37,
            "counterHard": 97,
            "counterTooHard": 107,
            "counterExHard": 168,
            "counterBrainFuck": 276
        },
        "ip": null,
        "playInfo": {
            "isActive": null,
            "expires_at": null
        },
        "labels": [],
        "recommended": 0
    },
    {
        "id": 551,
        "avatar": "/storage/avatars/1ea2980b9dc2d11cf6a3f82f10ba8702.png",
        "name": "Sau",
        "static_points": 20,
        "sp_flag": 0,
        "os": "Linux",
        "points": 20,
        "star": 4.6,
        "release": "2023-07-08T16:00:00.000000Z",
        "easy_month": 0,
        "poweroff": 0,
        "free": true,
        "difficulty": 30,
        "difficultyText": "Easy",
        "user_owns_count": 15306,
        "authUserInUserOwns": false,
        "root_owns_count": 14779,
        "authUserHasReviewed": false,
        "authUserInRootOwns": false,
        "isTodo": false,
        "is_competitive": false,
        "active": null,
        "feedbackForChart": {
            "counterCake": 2538,
            "counterVeryEasy": 2986,
            "counterEasy": 6476,
            "counterTooEasy": 3274,
            "counterMedium": 1115,
            "counterBitHard": 385,
            "counterHard": 215,
            "counterTooHard": 50,
            "counterExHard": 30,
            "counterBrainFuck": 101
        },
        "ip": null,
        "playInfo": {
            "isActive": null,
            "expires_at": null
        },
        "labels": [],
        "recommended": 0
    },
    {
        "id": 544,
        "avatar": "/storage/avatars/f0c89af6ee134e1b432d95e4528cf0cd.png",
        "name": "Bookworm",
        "static_points": 50,
        "sp_flag": 0,
        "os": "Linux",
        "points": 50,
        "star": 3.9,
        "release": "2023-05-27T16:00:00.000000Z",
        "easy_month": 0,
        "poweroff": 0,
        "free": true,
        "difficulty": 71,
        "difficultyText": "Insane",
        "user_owns_count": 880,
        "authUserInUserOwns": false,
        "root_owns_count": 682,
        "authUserHasReviewed": false,
        "authUserInRootOwns": false,
        "isTodo": false,
        "is_competitive": false,
        "active": null,
        "feedbackForChart": {
            "counterCake": 31,
            "counterVeryEasy": 18,
            "counterEasy": 36,
            "counterTooEasy": 50,
            "counterMedium": 80,
            "counterBitHard": 106,
            "counterHard": 215,
            "counterTooHard": 219,
            "counterExHard": 150,
            "counterBrainFuck": 139
        },
        "ip": null,
        "playInfo": {
            "isActive": null,
            "expires_at": null
        },
        "labels": [],
        "recommended": 0
    },
    {
        "id": 536,
        "avatar": "/storage/avatars/30fc6acef9d23aa9fd71277123c64f24.png",
        "name": "Coder",
        "static_points": 50,
        "sp_flag": 0,
        "os": "Windows",
        "points": 50,
        "star": 4.9,
        "release": "2023-04-01T16:00:00.000000Z",
        "easy_month": 0,
        "poweroff": 0,
        "free": true,
        "difficulty": 77,
        "difficultyText": "Insane",
        "user_owns_count": 1109,
        "authUserInUserOwns": false,
        "root_owns_count": 886,
        "authUserHasReviewed": false,
        "authUserInRootOwns": false,
        "isTodo": false,
        "is_competitive": false,
        "active": null,
        "feedbackForChart": {
            "counterCake": 30,
            "counterVeryEasy": 8,
            "counterEasy": 15,
            "counterTooEasy": 33,
            "counterMedium": 82,
            "counterBitHard": 103,
            "counterHard": 235,
            "counterTooHard": 309,
            "counterExHard": 229,
            "counterBrainFuck": 251
        },
        "ip": null,
        "playInfo": {
            "isActive": null,
            "expires_at": null
        },
        "labels": [],
        "recommended": 0
    }
]